LICENSE
README.md
setup.py
./fightingcv_attention/__init__.py
./fightingcv_attention/attention/A2Atttention.py
./fightingcv_attention/attention/ACmixAttention.py
./fightingcv_attention/attention/AFT.py
./fightingcv_attention/attention/Axial_attention.py
./fightingcv_attention/attention/BAM.py
./fightingcv_attention/attention/CBAM.py
./fightingcv_attention/attention/CoAtNet.py
./fightingcv_attention/attention/CoTAttention.py
./fightingcv_attention/attention/CoordAttention.py
./fightingcv_attention/attention/CrissCrossAttention.py
./fightingcv_attention/attention/Crossformer.py
./fightingcv_attention/attention/DANet.py
./fightingcv_attention/attention/DAT.py
./fightingcv_attention/attention/ECAAttention.py
./fightingcv_attention/attention/EMSA.py
./fightingcv_attention/attention/ExternalAttention.py
./fightingcv_attention/attention/HaloAttention.py
./fightingcv_attention/attention/MOATransformer.py
./fightingcv_attention/attention/MUSEAttention.py
./fightingcv_attention/attention/MobileViTAttention.py
./fightingcv_attention/attention/MobileViTv2Attention.py
./fightingcv_attention/attention/OutlookAttention.py
./fightingcv_attention/attention/PSA.py
./fightingcv_attention/attention/ParNetAttention.py
./fightingcv_attention/attention/PolarizedSelfAttention.py
./fightingcv_attention/attention/ResidualAttention.py
./fightingcv_attention/attention/S2Attention.py
./fightingcv_attention/attention/SEAttention.py
./fightingcv_attention/attention/SGE.py
./fightingcv_attention/attention/SKAttention.py
./fightingcv_attention/attention/SelfAttention.py
./fightingcv_attention/attention/ShuffleAttention.py
./fightingcv_attention/attention/SimAM.py
./fightingcv_attention/attention/SimplifiedSelfAttention.py
./fightingcv_attention/attention/TripletAttention.py
./fightingcv_attention/attention/UFOAttention.py
./fightingcv_attention/attention/ViP.py
./fightingcv_attention/attention/__init__.py
./fightingcv_attention/attention/gfnet.py
./fightingcv_attention/backbone/CMT.py
fightingcv_attention.egg-info/PKG-INFO
fightingcv_attention.egg-info/SOURCES.txt
fightingcv_attention.egg-info/dependency_links.txt
fightingcv_attention.egg-info/top_level.txt