Metadata-Version: 2.1
Name: fightingcv-attention
Version: 1.0.0
Summary: FightingCV Codebase For Attention,Backbone, MLP, Re-parameter, Convolution
Home-page: https://github.com/xmu-xiaoma666/External-Attention-pytorch
Author: fightingcv
Author-email: hello@fightingcv.com
License: Apache
Keywords: AttentionBackbone
Platform: UNKNOWN
Classifier: Intended Audience :: Developers
Classifier: Intended Audience :: Education
Classifier: Intended Audience :: Science/Research
Classifier: License :: OSI Approved :: Apache Software License
Classifier: Operating System :: OS Independent
Classifier: Programming Language :: Python :: 3
Classifier: Topic :: Scientific/Engineering :: Artificial Intelligence
Requires-Python: >=3.7.0
License-File: LICENSE
